{
  "ComponentIndexes": {},
  "ControlUniqueGuids": {},
  "ControlUniqueIds": {
    "Algorithms": 138,
    "App": 1,
    "assignment input": 3,
    "Assignments": 92,
    "assignments screen": 49,
    "Body3": 61,
    "Body3_1": 63,
    "Button1": 88,
    "Button1_1": 89,
    "Button1_2": 90,
    "Button1_3": 91,
    "Button1_4": 133,
    "Button1_5": 134,
    "Button1_6": 135,
    "Button1_7": 136,
    "Button1_8": 137,
    "Button2": 24,
    "Button3": 117,
    "Button4": 48,
    "Circle1": 45,
    "Circle1_1": 87,
    "Circle1_2": 47,
    "classes screen": 93,
    "course work screen": 25,
    "DataCardKey1": 20,
    "DataCardKey2": 11,
    "DataCardKey3": 15,
    "DataCardValue1": 22,
    "DataCardValue2": 12,
    "DataCardValue3": 17,
    "Description_DataCard1": 19,
    "Due date_DataCard1": 14,
    "ErrorMessage1": 23,
    "ErrorMessage2": 13,
    "ErrorMessage3": 18,
    "Form1": 9,
    "Gallery1": 126,
    "Gallery1_6": 74,
    "Gallery3": 99,
    "Gallery4": 59,
    "Gallery5": 110,
    "galleryTemplate1": 127,
    "galleryTemplate1_6": 75,
    "galleryTemplate3": 100,
    "galleryTemplate4": 60,
    "galleryTemplate5": 111,
    "Icon1": 85,
    "Icon2": 95,
    "Icon2_1": 27,
    "Icon2_2": 53,
    "Icon2_3": 121,
    "Icon2_4": 6,
    "Icon2_5": 67,
    "Icon2_6": 38,
    "Icon2_7": 140,
    "Icon3": 51,
    "Icon4": 54,
    "Icon4_1": 7,
    "Icon4_2": 39,
    "Icon4_3": 152,
    "Label1": 84,
    "Label10": 120,
    "Label10_1": 37,
    "Label11": 42,
    "Label12": 96,
    "Label14": 44,
    "Label15": 41,
    "Label15_1": 43,
    "Label15_2": 40,
    "Label16": 46,
    "Label18": 28,
    "Label18_1": 141,
    "Label2": 147,
    "Label2_1": 148,
    "Label2_10": 158,
    "Label2_11": 159,
    "Label2_12": 160,
    "Label2_13": 161,
    "Label2_14": 162,
    "Label2_16": 164,
    "Label2_17": 165,
    "Label2_18": 166,
    "Label2_19": 167,
    "Label2_2": 149,
    "Label2_3": 150,
    "Label2_4": 151,
    "Label2_5": 153,
    "Label2_6": 154,
    "Label2_7": 155,
    "Label2_8": 156,
    "Label2_9": 157,
    "Label20": 104,
    "Label20_1": 105,
    "Label20_2": 107,
    "Label20_3": 102,
    "Label21": 98,
    "Label24": 101,
    "Label25": 103,
    "Label26": 106,
    "Label27": 108,
    "Label3": 52,
    "Label3_1": 5,
    "Label4": 122,
    "Label4_1": 123,
    "Label4_2": 124,
    "Label4_3": 125,
    "Label4_5": 69,
    "Label4_6": 70,
    "Label4_7": 71,
    "Label4_8": 72,
    "Label4_9": 73,
    "Label5": 68,
    "Label6": 86,
    "Label7": 55,
    "Label7_1": 57,
    "Label7_2": 58,
    "Label7_3": 56,
    "Label8": 8,
    "Label9": 97,
    "Label9_1": 109,
    "Rectangle1": 83,
    "Rectangle1_1": 94,
    "Rectangle1_2": 26,
    "Rectangle1_3": 50,
    "Rectangle1_4": 119,
    "Rectangle1_5": 4,
    "Rectangle1_6": 66,
    "Rectangle1_7": 36,
    "Rectangle1_8": 139,
    "revision screen": 118,
    "Revision summary": 35,
    "Separator2": 132,
    "Separator3_1": 81,
    "StarVisible1": 21,
    "StarVisible3": 16,
    "Subject_DataCard1": 10,
    "Subtitle8": 64,
    "Tasks dashboard": 82,
    "timetable": 65,
    "Title2": 131,
    "Title2_1": 128,
    "Title2_2": 129,
    "Title2_3": 130,
    "Title3_1": 76,
    "Title3_2": 77,
    "Title3_3": 78,
    "Title3_4": 79,
    "Title3_5": 80,
    "Title8": 112,
    "Title8_1": 113,
    "Title8_2": 114,
    "Title8_3": 115,
    "Title8_4": 116,
    "Title9": 62
  },
  "FunctionParamsInvariantScripts": {},
  "FunctionParamsInvariantScriptsOnInstances": {},
  "HeaderLastSavedDateTimeUTC": "09/30/2022 14:35:36",
  "IsLegacyComponentAllowGlobalScopeCase": false,
  "LocalConnectionIDReferences": {
    "95efe64d-ac2f-4c01-97a3-3fc27ee8c942": "\"/providers/microsoft.powerapps/apis/shared_sharepointonline/connections/a78553803563429ca7c71a604db8ce83\""
  },
  "LocalDatabaseReferencesAsEmpty": false,
  "LocalResourceFileNames": {},
  "LocalResourceRootPaths": {},
  "OrderComponentMetadata": {},
  "OrderComponentTemplate": {},
  "OrderDataSource": {
    "assignments": 0,
    "classes": 2,
    "Coursework": 4,
    "CustomGallerySample": 1,
    "revision": 3
  },
  "OrderGroupControls": {
    "Assignments": {
      "Button1_1": 1,
      "Circle1_1": 0
    }
  },
  "OrderPcfTemplate": {},
  "OrderTemplate": {},
  "OrderXMLTemplate": {
    "button": 6,
    "circle": 7,
    "datepicker": 5,
    "form": 3,
    "gallery": 8,
    "icon": 2,
    "label": 1,
    "rectangle": 0,
    "text": 4
  },
  "PublishOrderIndices": {
    "Algorithms": 0,
    "App": 0,
    "assignment input": 0,
    "Assignments": 4,
    "assignments screen": 0,
    "Body3": 53,
    "Body3_1": 55,
    "Button1": 6,
    "Button1_1": 7,
    "Button1_2": 8,
    "Button1_3": 9,
    "Button1_4": 37,
    "Button1_5": 39,
    "Button1_6": 38,
    "Button1_7": 41,
    "Button1_8": 40,
    "Button2": 91,
    "Button3": 33,
    "Button4": 120,
    "Circle1": 117,
    "Circle1_1": 5,
    "Circle1_2": 119,
    "classes screen": 0,
    "course work screen": 0,
    "DataCardKey1": 87,
    "DataCardKey2": 78,
    "DataCardKey3": 82,
    "DataCardValue1": 89,
    "DataCardValue2": 79,
    "DataCardValue3": 84,
    "Description_DataCard1": 86,
    "Due date_DataCard1": 81,
    "ErrorMessage1": 90,
    "ErrorMessage2": 80,
    "ErrorMessage3": 85,
    "Form1": 76,
    "Gallery1": 64,
    "Gallery1_6": 100,
    "Gallery3": 15,
    "Gallery4": 51,
    "Gallery5": 26,
    "galleryTemplate1": 65,
    "galleryTemplate1_6": 101,
    "galleryTemplate3": 16,
    "galleryTemplate4": 52,
    "galleryTemplate5": 27,
    "Icon1": 2,
    "Icon2": 11,
    "Icon2_1": 35,
    "Icon2_2": 45,
    "Icon2_3": 59,
    "Icon2_4": 73,
    "Icon2_5": 93,
    "Icon2_6": 110,
    "Icon2_7": 122,
    "Icon3": 43,
    "Icon4": 46,
    "Icon4_1": 74,
    "Icon4_2": 111,
    "Icon4_3": 124,
    "Label1": 1,
    "Label10": 58,
    "Label10_1": 109,
    "Label11": 114,
    "Label12": 12,
    "Label14": 116,
    "Label15": 113,
    "Label15_1": 115,
    "Label15_2": 112,
    "Label16": 118,
    "Label18": 36,
    "Label18_1": 123,
    "Label2": 126,
    "Label2_1": 128,
    "Label2_10": 135,
    "Label2_11": 137,
    "Label2_12": 139,
    "Label2_13": 141,
    "Label2_14": 143,
    "Label2_16": 136,
    "Label2_17": 138,
    "Label2_18": 140,
    "Label2_19": 142,
    "Label2_2": 130,
    "Label2_3": 132,
    "Label2_4": 134,
    "Label2_5": 125,
    "Label2_6": 127,
    "Label2_7": 129,
    "Label2_8": 131,
    "Label2_9": 133,
    "Label20": 20,
    "Label20_1": 21,
    "Label20_2": 23,
    "Label20_3": 18,
    "Label21": 14,
    "Label24": 17,
    "Label25": 19,
    "Label26": 22,
    "Label27": 24,
    "Label3": 44,
    "Label3_1": 72,
    "Label4": 60,
    "Label4_1": 61,
    "Label4_2": 62,
    "Label4_3": 63,
    "Label4_5": 95,
    "Label4_6": 96,
    "Label4_7": 97,
    "Label4_8": 98,
    "Label4_9": 99,
    "Label5": 94,
    "Label6": 3,
    "Label7": 47,
    "Label7_1": 49,
    "Label7_2": 50,
    "Label7_3": 48,
    "Label8": 75,
    "Label9": 13,
    "Label9_1": 25,
    "Rectangle1": 0,
    "Rectangle1_1": 10,
    "Rectangle1_2": 34,
    "Rectangle1_3": 42,
    "Rectangle1_4": 57,
    "Rectangle1_5": 71,
    "Rectangle1_6": 92,
    "Rectangle1_7": 108,
    "Rectangle1_8": 121,
    "revision screen": 0,
    "Revision summary": 0,
    "Separator2": 70,
    "Separator3_1": 107,
    "StarVisible1": 88,
    "StarVisible3": 83,
    "Subject_DataCard1": 77,
    "Subtitle8": 56,
    "Tasks dashboard": 0,
    "timetable": 0,
    "Title2": 69,
    "Title2_1": 66,
    "Title2_2": 67,
    "Title2_3": 68,
    "Title3_1": 102,
    "Title3_2": 103,
    "Title3_3": 104,
    "Title3_4": 105,
    "Title3_5": 106,
    "Title8": 28,
    "Title8_1": 29,
    "Title8_2": 30,
    "Title8_3": 31,
    "Title8_4": 32,
    "Title9": 54
  },
  "ResourcesJsonIndices": {
    "Image-SampleImage": 0
  },
  "RuleScreenIdWithoutScreen": {},
  "TemplateVersions": {},
  "VolatileProperties": {
    "AnalysisLoadTime": 0.8858426,
    "ControlCount": {
      "button": 17,
      "circle": 3,
      "datepicker": 1,
      "form": 1,
      "gallery": 6,
      "galleryTemplate": 6,
      "group": 1,
      "icon": 14,
      "label": 90,
      "rectangle": 12,
      "screen": 8,
      "text": 2,
      "typedDataCard": 3
    },
    "DeserializationLoadTime": 1.5052505,
    "ErrorCount": 0
  },
  "WasLocalDatabaseReferencesEmpty": true
}